sslcontext_factory/__init__.py
sslcontext_factory/factory.py
sslcontext_factory/_extras/__init__.py
sslcontext_factory/_extras/urllib3.py
sslcontext_factory-0.1.2.dist-info/METADATA
sslcontext_factory-0.1.2.dist-info/WHEEL
sslcontext_factory-0.1.2.dist-info/top_level.txt
sslcontext_factory-0.1.2.dist-info/RECORD
