Metadata-Version: 2.1
Name: sslcontext-factory
Version: 0.1.2
Summary: Tool to create a sslcontext factory, and extras such as the option to inject this library into urllib3 (or pip)
Home-page: https://github.com/jose-pr/pypki
Author: Jose A.
Author-email: jose-pr@coqui.dev
License: UNKNOWN
Platform: UNKNOWN
Requires-Dist: sslcontext (>=1.3.0)
